monoformat/__init__.py
monoformat/__main__.py
monoformat/exceptions.py
monoformat/explorer.py
monoformat/formatters.py
monoformat-0.2.0.dist-info/LICENSE
monoformat-0.2.0.dist-info/METADATA
monoformat-0.2.0.dist-info/WHEEL
monoformat-0.2.0.dist-info/entry_points.txt
monoformat-0.2.0.dist-info/RECORD
