Metadata-Version: 2.1
Name: monoformat
Version: 0.2.0
Summary: A tool that formats all kinds of languages consistently
Home-page: https://github.com/Xowap/Monoformat
License: WTFPL
Author: Rémy Sanchez
Author-email: remy.sanchez@hyperthese.net
Requires-Python: >=3.10,<4.0
Classifier: License :: Other/Proprietary License
Classifier: Programming Language :: Python :: 3
Classifier: Programming Language :: Python :: 3.10
Classifier: Programming Language :: Python :: 3.11
Requires-Dist: black (==23.*)
Requires-Dist: colorama (>=0.4.6,<0.5.0)
Requires-Dist: isort (>=5.10.1,<6.0.0)
Requires-Dist: node-edge (>=0.1.0b2,<0.2.0)
Requires-Dist: pathspec (>=0.11.0,<0.12.0)
Project-URL: Repository, https://github.com/Xowap/Monoformat
